{
    "amenity-bench": 61697,
    "amenity-information-information": 61698,
    "amenity-information-post_box": 61699,
    "amenity-information-telephone": 61700,
    "amenity-sanitary-drinking_water": 61701,
    "amenity-sanitary-shower": 61702,
    "amenity-sanitary-toilets": 61703,
    "amenity-stile": 61704,
    "amenity-waste-centre": 61705,
    "amenity-waste-container": 61706,
    "amenity-waste-dog_excrement": 61707,
    "amenity-waste-sanitary_dump_station": 61708,
    "amenity-waste-vending_machine": 61709,
    "amenity-waste-waste_basket": 61710,
    "amenity-waste-waste_disposal": 61711,
    "amenity": 61712,
    "catering-drink-bar": 61713,
    "catering-drink-cafe": 61714,
    "catering-drink-pub": 61715,
    "catering-food-caterer": 61716,
    "catering-food-fast_food": 61717,
    "catering-food-food_court": 61718,
    "catering-food-ice_cream": 61719,
    "catering-food-pastry": 61720,
    "catering-food-restaurant": 61721,
    "catering": 61722,
    "convenience-bakery": 61723,
    "convenience-butcher": 61724,
    "convenience-cheese": 61725,
    "convenience-chemist": 61726,
    "convenience-convenience": 61727,
    "convenience-dressmaker": 61728,
    "convenience-florist": 61729,
    "convenience-greengrocer": 61730,
    "convenience-hairdresser": 61731,
    "convenience-kiosk": 61732,
    "convenience-marketplace": 61733,
    "convenience-newsagent": 61734,
    "convenience-photo": 61735,
    "convenience-seafood": 61736,
    "convenience-shoemaker": 61737,
    "convenience-sports": 61738,
    "convenience-supermarket": 61739,
    "convenience-tobacco": 61740,
    "convenience": 61741,
    "culture-artwork": 61742,
    "culture-historic-archaeological_site": 61743,
    "culture-historic-castle_wall": 61744,
    "culture-historic-castle": 61745,
    "culture-historic-church": 61746,
    "culture-historic-city_gate": 61747,
    "culture-historic-city_wall": 61748,
    "culture-historic-memorial": 61749,
    "culture-historic-monument": 61750,
    "culture-historic-wayside_cross": 61751,
    "culture-historic-wayside_shrine": 61752,
    "culture-historic": 61753,
    "culture-library": 61754,
    "culture-public_bookcase": 61755,
    "culture-show-cinema": 61756,
    "culture-show-gallery": 61757,
    "culture-show-theatre": 61758,
    "culture-visit-arts_centre": 61759,
    "culture-visit-cathedral": 61760,
    "culture-visit-chapel": 61761,
    "culture-visit-church": 61762,
    "culture-visit-museum": 61763,
    "culture-visit-place_of_worship": 61764,
    "culture": 61765,
    "extra-abbey": 61766,
    "extra-aeroport": 61767,
    "extra-ambassador": 61768,
    "extra-arenes": 61769,
    "extra-artisan-prestige": 61770,
    "extra-autres_sports": 61771,
    "extra-balade_maritime": 61772,
    "extra-balneotherapy": 61773,
    "extra-bike_ride": 61774,
    "extra-bungee_jumping": 61775,
    "extra-canyoning": 61776,
    "extra-cheese_maker": 61777,
    "extra-commerce-prestige": 61778,
    "extra-conserveur_prestige": 61779,
    "extra-conserveurs": 61780,
    "extra-convent": 61781,
    "extra-delivery": 61782,
    "extra-drive": 61783,
    "extra-equipements_loisirs": 61784,
    "extra-escape_game": 61785,
    "extra-excursion": 61786,
    "extra-ferme_decouverte": 61787,
    "extra-fish_market": 61788,
    "extra-flower_village": 61789,
    "extra-fontaine_miraculeuse": 61790,
    "extra-food_truck": 61791,
    "extra-food": 61792,
    "extra-ganaderia": 61793,
    "extra-gratuiterie": 61794,
    "extra-guided_hikes": 61795,
    "extra-guided_tour": 61796,
    "extra-hebergement_insolite": 61797,
    "extra-hiking": 61798,
    "extra-kitchen_designer": 61799,
    "extra-laboratory": 61800,
    "extra-lost-property": 61801,
    "extra-major_projects": 61802,
    "extra-mediatheque": 61803,
    "extra-medical_supply": 61804,
    "extra-natural_site": 61805,
    "extra-nature_reserve": 61806,
    "extra-notary": 61807,
    "extra-nurse": 61808,
    "extra-organic_store": 61809,
    "extra-oyster_hut": 61810,
    "extra-paddle": 61811,
    "extra-pignada": 61812,
    "extra-pique_nique_prestige": 61813,
    "extra-podiatrist": 61814,
    "extra-quillier": 61815,
    "extra-rando": 61816,
    "extra-recycling": 61817,
    "extra-reflexology": 61818,
    "extra-restaurateurs-prestige": 61819,
    "extra-restricted": 61820,
    "extra-shared_garden": 61821,
    "extra-speleology": 61822,
    "extra-sports_and_leisures": 61823,
    "extra-sports_d_eau": 61824,
    "extra-spot_surf": 61825,
    "extra-squash": 61826,
    "extra-surfhouses": 61827,
    "extra-terra_aventura": 61828,
    "extra-thermal_establishment": 61829,
    "extra-thermal_station": 61830,
    "extra-to_take_away": 61831,
    "extra-unavoidable": 61832,
    "extra-unesco_site": 61833,
    "extra-usefull": 61834,
    "extra-velo_repare": 61835,
    "extra-vine": 61836,
    "extra-vote_place": 61837,
    "extra-vtt": 61838,
    "extra-wash_house": 61839,
    "extra-WIFI": 61840,
    "extra-zip_line": 61841,
    "hosting-hotel-guest_house": 61842,
    "hosting-hotel-hostel": 61843,
    "hosting-hotel-hotel": 61844,
    "hosting-hotel-motel": 61845,
    "hosting-rental-apartment": 61846,
    "hosting-rental-chalet": 61847,
    "hosting-resort-apartment": 61848,
    "hosting-resort-camp_site": 61849,
    "hosting-resort-caravan_site": 61850,
    "hosting-resort-resort": 61851,
    "hosting": 61852,
    "layers-peak": 61853,
    "leisure-bowling_alley": 61854,
    "leisure-casino": 61855,
    "leisure-community_centre": 61856,
    "leisure-fitness_centre": 61857,
    "leisure-golf_course": 61858,
    "leisure-hide-bird_hide": 61859,
    "leisure-hide-tower": 61860,
    "leisure-hide-wildlife_hide": 61861,
    "leisure-horse_riding": 61862,
    "leisure-hut-alpine_hut": 61863,
    "leisure-hut-shelter": 61864,
    "leisure-hut-wilderness_hut": 61865,
    "leisure-ice_rink": 61866,
    "leisure-miniature_golf": 61867,
    "leisure-nightclub": 61868,
    "leisure-park-garden": 61869,
    "leisure-park-park": 61870,
    "leisure-pelota": 61871,
    "leisure-picnic-bbq": 61872,
    "leisure-picnic-firepit": 61873,
    "leisure-picnic-picnic_site": 61874,
    "leisure-picnic-picnic_table": 61875,
    "leisure-pitch": 61876,
    "leisure-playground": 61877,
    "leisure-public_bath": 61878,
    "leisure-sport-athletics": 61879,
    "leisure-sport-badminton": 61880,
    "leisure-sport-basketball": 61881,
    "leisure-sport-beachvolleyball": 61882,
    "leisure-sport-billiards": 61883,
    "leisure-sport-bmx": 61884,
    "leisure-sport-boules": 61885,
    "leisure-sport-bullfighting": 61886,
    "leisure-sport-canoe": 61887,
    "leisure-sport-climbing_adventure": 61888,
    "leisure-sport-climbing": 61889,
    "leisure-sport-cycling": 61890,
    "leisure-sport-diving": 61891,
    "leisure-sport-equestrian": 61892,
    "leisure-sport-free_flying": 61893,
    "leisure-sport-futsal": 61894,
    "leisure-sport-golf": 61895,
    "leisure-sport-gymnastics": 61896,
    "leisure-sport-handball": 61897,
    "leisure-sport-horse_racing": 61898,
    "leisure-sport-ice_hockey": 61899,
    "leisure-sport-karting": 61900,
    "leisure-sport-kitesurfing": 61901,
    "leisure-sport-motocross": 61902,
    "leisure-sport-motor": 61903,
    "leisure-sport-multi": 61904,
    "leisure-sport-orienteering": 61905,
    "leisure-sport-paddle_tennis": 61906,
    "leisure-sport-paintball": 61907,
    "leisure-sport-pelota": 61908,
    "leisure-sport-racquet": 61909,
    "leisure-sport-rowing": 61910,
    "leisure-sport-rugby_league": 61911,
    "leisure-sport-rugby_union": 61912,
    "leisure-sport-rugby": 61913,
    "leisure-sport-running": 61914,
    "leisure-sport-sailing": 61915,
    "leisure-sport-scuba_diving": 61916,
    "leisure-sport-shooting": 61917,
    "leisure-sport-skateboard": 61918,
    "leisure-sport-soccer": 61919,
    "leisure-sport-squash": 61920,
    "leisure-sport-surfing": 61921,
    "leisure-sport-swimming": 61922,
    "leisure-sport-table_soccer": 61923,
    "leisure-sport-table_tennis": 61924,
    "leisure-sport-tennis": 61925,
    "leisure-sport-volleyball": 61926,
    "leisure-sport-water_ski": 61927,
    "leisure-sport-yoga": 61928,
    "leisure-sport": 61929,
    "leisure-sports_centre": 61930,
    "leisure-surfing": 61931,
    "leisure-swimming_pool": 61932,
    "leisure-swimming": 61933,
    "leisure": 61934,
    "mobility-aeroway-aerodrome": 61935,
    "mobility-bicycle-bicycle_parking": 61936,
    "mobility-bicycle-bicycle_rental": 61937,
    "mobility-bicycle-bicycle": 61938,
    "mobility-bicycle-compressed_air": 61939,
    "mobility-bicycle-cycle_barrier": 61940,
    "mobility-bicycle-motorcycle_parking": 61941,
    "mobility-bicycle": 61942,
    "mobility-charging_station": 61943,
    "mobility-motorway-bus_station": 61944,
    "mobility-motorway-bus_stop": 61945,
    "mobility-motorway-car_pooling": 61946,
    "mobility-motorway-car_rental": 61947,
    "mobility-motorway-motorway_junction": 61948,
    "mobility-motorway-parking": 61949,
    "mobility-motorway-taxi": 61950,
    "mobility-motorway-toll_booth": 61951,
    "mobility-railway-halt": 61952,
    "mobility-railway-station": 61953,
    "mobility-railway-subway_entrance": 61954,
    "mobility-railway-tram_stop": 61955,
    "mobility-railway": 61956,
    "mobility-waterway-dock": 61957,
    "mobility-waterway-ferry_terminal": 61958,
    "mobility": 61959,
    "products-alcohol": 61960,
    "products-carpet": 61961,
    "products-chocolate": 61962,
    "products-craft-basket_maker": 61963,
    "products-craft-beekeeper": 61964,
    "products-craft-brewery": 61965,
    "products-craft-distillery": 61966,
    "products-craft-grinding_mill": 61967,
    "products-craft-handicraft": 61968,
    "products-craft-jeweller": 61969,
    "products-craft-leather": 61970,
    "products-craft-luthier": 61971,
    "products-craft-pottery": 61972,
    "products-craft-sculptor": 61973,
    "products-craft-winery": 61974,
    "products-craft": 61975,
    "products-deli": 61976,
    "products-farm": 61977,
    "products-oil_mill": 61978,
    "products-tailor": 61979,
    "products": 61980,
    "public_landmark-border_control": 61981,
    "public_landmark-brownfield": 61982,
    "public_landmark-cemetery": 61983,
    "public_landmark-college": 61984,
    "public_landmark-courthouse": 61985,
    "public_landmark-embassy": 61986,
    "public_landmark-grave_yard": 61987,
    "public_landmark-kindergarten": 61988,
    "public_landmark-library": 61989,
    "public_landmark-mall": 61990,
    "public_landmark-prison": 61991,
    "public_landmark-school": 61992,
    "public_landmark-university": 61993,
    "public_landmark-yes": 61994,
    "public_landmark": 61995,
    "remarkable-attraction_activity-aquarium": 61996,
    "remarkable-attraction_activity-attraction": 61997,
    "remarkable-attraction_activity-cave_entrance": 61998,
    "remarkable-attraction_activity-lighthouse": 61999,
    "remarkable-attraction_activity-spring": 62000,
    "remarkable-attraction_activity-theme_park": 62001,
    "remarkable-attraction_activity-viewpoint": 62002,
    "remarkable-attraction_activity-water_park": 62003,
    "remarkable-attraction_activity-waterfall": 62004,
    "remarkable-attraction_activity-zoo": 62005,
    "remarkable-natural_activity-beach_resort": 62006,
    "remarkable-natural_activity-beach": 62007,
    "remarkable-outdoor_activity-fishing": 62008,
    "remarkable-outdoor_activity-marina": 62009,
    "remarkable-outdoor_activity-stadium": 62010,
    "remarkable-outdoor_activity-swimming_area": 62011,
    "remarkable-outdoor_activity-winter_sports": 62012,
    "remarkable": 62013,
    "safety-care-centre": 62014,
    "safety-care-dentist": 62015,
    "safety-care-doctors": 62016,
    "safety-care-pharmacy": 62017,
    "safety-care-physiotherapist": 62018,
    "safety-care-veterinary": 62019,
    "safety-emergency-clinic": 62020,
    "safety-emergency-defibrillator": 62021,
    "safety-emergency-hospital": 62022,
    "safety-rescue-fire_station": 62023,
    "safety-rescue-life_ring": 62024,
    "safety-rescue-lifeguard_base": 62025,
    "safety-rescue-mountain_rescue": 62026,
    "safety-rescue-police": 62027,
    "safety-rescue-water_rescue_station": 62028,
    "safety": 62029,
    "services-atm": 62030,
    "services-bank": 62031,
    "services-car_parts": 62032,
    "services-car_repair": 62033,
    "services-copyshop": 62034,
    "services-coworking_space": 62035,
    "services-dry_cleaning": 62036,
    "services-estate_agent": 62037,
    "services-fuel": 62038,
    "services-laundry": 62039,
    "services-massage": 62040,
    "services-office": 62041,
    "services-post_office": 62042,
    "services-ticket": 62043,
    "services-townhall": 62044,
    "services-travel_agency": 62045,
    "services": 62046,
    "shopping-animals-pet_grooming": 62047,
    "shopping-animals-pet": 62048,
    "shopping-culture-antiques": 62049,
    "shopping-culture-art": 62050,
    "shopping-culture-books": 62051,
    "shopping-culture-music": 62052,
    "shopping-fashion-accessories": 62053,
    "shopping-fashion-bag": 62054,
    "shopping-fashion-boutique": 62055,
    "shopping-fashion-clothes": 62056,
    "shopping-fashion-cosmetics": 62057,
    "shopping-fashion-fabric": 62058,
    "shopping-fashion-gift": 62059,
    "shopping-fashion-interior_decoration": 62060,
    "shopping-fashion-jewelry": 62061,
    "shopping-fashion-perfume": 62062,
    "shopping-fashion-perfumery": 62063,
    "shopping-fashion-second_hand": 62064,
    "shopping-fashion-shoes": 62065,
    "shopping-fashion-tattoo": 62066,
    "shopping-fashion-watches": 62067,
    "shopping-feed-beverages": 62068,
    "shopping-feed-coffee": 62069,
    "shopping-feed-confectionery": 62070,
    "shopping-feed-frozen_food": 62071,
    "shopping-feed-ice_cream": 62072,
    "shopping-sport_supply-bicycle": 62073,
    "shopping-sport_supply-fishing": 62074,
    "shopping-sport_supply-outdoor": 62075,
    "shopping-sport_supply-sports": 62076,
    "shopping-supply-bed": 62077,
    "shopping-supply-camera": 62078,
    "shopping-supply-charity": 62079,
    "shopping-supply-computer": 62080,
    "shopping-supply-doityourself": 62081,
    "shopping-supply-electronics": 62082,
    "shopping-supply-erotic": 62083,
    "shopping-supply-furniture": 62084,
    "shopping-supply-general": 62085,
    "shopping-supply-hardware": 62086,
    "shopping-supply-hearing_aids": 62087,
    "shopping-supply-hifi": 62088,
    "shopping-supply-lamps": 62089,
    "shopping-supply-mobile_phone": 62090,
    "shopping-supply-motorcycle": 62091,
    "shopping-supply-musical_instrument": 62092,
    "shopping-supply-optician": 62093,
    "shopping-supply-stationery": 62094,
    "shopping-supply-toys": 62095,
    "shopping-supply-video_games": 62096,
    "shopping-supply-video": 62097,
    "shopping-supply-weapons": 62098,
    "shopping-supply-wholesale": 62099,
    "shopping": 62100
}