{
    "amenity-bench": 61697,
    "amenity-information-information": 61698,
    "amenity-information-post_box": 61699,
    "amenity-information-telephone": 61700,
    "amenity-sanitary-drinking_water": 61701,
    "amenity-sanitary-shower": 61702,
    "amenity-sanitary-toilets": 61703,
    "amenity-stile": 61704,
    "amenity-waste-centre": 61705,
    "amenity-waste-container": 61706,
    "amenity-waste-dog_excrement": 61707,
    "amenity-waste-vending_machine": 61708,
    "amenity-waste-waste_basket": 61709,
    "amenity-waste-waste_disposal": 61710,
    "amenity": 61711,
    "catering-drink-bar": 61712,
    "catering-drink-cafe": 61713,
    "catering-drink-pub": 61714,
    "catering-food-fast_food": 61715,
    "catering-food-food_court": 61716,
    "catering-food-ice_cream": 61717,
    "catering-food-pastry": 61718,
    "catering-food-restaurant": 61719,
    "catering": 61720,
    "convenience-bakery": 61721,
    "convenience-butcher": 61722,
    "convenience-chemist": 61723,
    "convenience-florist": 61724,
    "convenience-greengrocer": 61725,
    "convenience-hairdresser": 61726,
    "convenience-kiosk": 61727,
    "convenience-marketplace": 61728,
    "convenience-newsagent": 61729,
    "convenience-photo": 61730,
    "convenience-seafood": 61731,
    "convenience-sports": 61732,
    "convenience-supermarket": 61733,
    "convenience-tobacco": 61734,
    "convenience": 61735,
    "culture-artwork": 61736,
    "culture-historic-archaeological_site": 61737,
    "culture-historic-castle_wall": 61738,
    "culture-historic-castle": 61739,
    "culture-historic-church": 61740,
    "culture-historic-city_gate": 61741,
    "culture-historic-city_wall": 61742,
    "culture-historic-memorial": 61743,
    "culture-historic-monument": 61744,
    "culture-historic-wayside_cross": 61745,
    "culture-historic-wayside_shrine": 61746,
    "culture-historic": 61747,
    "culture-show-cinema": 61748,
    "culture-show-gallery": 61749,
    "culture-show-theatre": 61750,
    "culture-visit-arts_centre": 61751,
    "culture-visit-cathedral": 61752,
    "culture-visit-chapel": 61753,
    "culture-visit-church": 61754,
    "culture-visit-museum": 61755,
    "culture-visit-place_of_worship": 61756,
    "culture": 61757,
    "hosting-hotel-guest_house": 61758,
    "hosting-hotel-hostel": 61759,
    "hosting-hotel-hotel": 61760,
    "hosting-hotel-motel": 61761,
    "hosting-rental-apartment": 61762,
    "hosting-rental-chalet": 61763,
    "hosting-resort-apartment": 61764,
    "hosting-resort-camp_site": 61765,
    "hosting-resort-caravan_site": 61766,
    "hosting-resort-resort": 61767,
    "hosting": 61768,
    "layers-peak": 61769,
    "leisure-bowling_alley": 61770,
    "leisure-casino": 61771,
    "leisure-community_centre": 61772,
    "leisure-fitness_centre": 61773,
    "leisure-golf_course": 61774,
    "leisure-hide-bird_hide": 61775,
    "leisure-hide-tower": 61776,
    "leisure-hide-wildlife_hide": 61777,
    "leisure-horse_riding": 61778,
    "leisure-hut-alpine_hut": 61779,
    "leisure-hut-shelter": 61780,
    "leisure-hut-wilderness_hut": 61781,
    "leisure-ice_rink": 61782,
    "leisure-miniature_golf": 61783,
    "leisure-nightclub": 61784,
    "leisure-park-garden": 61785,
    "leisure-park-park": 61786,
    "leisure-pelota": 61787,
    "leisure-picnic-bbq": 61788,
    "leisure-picnic-firepit": 61789,
    "leisure-picnic-picnic_site": 61790,
    "leisure-picnic-picnic_table": 61791,
    "leisure-pitch": 61792,
    "leisure-playground": 61793,
    "leisure-public_bath": 61794,
    "leisure-sport-athletics": 61795,
    "leisure-sport-badminton": 61796,
    "leisure-sport-basketball": 61797,
    "leisure-sport-beachvolleyball": 61798,
    "leisure-sport-billiards": 61799,
    "leisure-sport-bmx": 61800,
    "leisure-sport-boules": 61801,
    "leisure-sport-bullfighting": 61802,
    "leisure-sport-canoe": 61803,
    "leisure-sport-climbing_adventure": 61804,
    "leisure-sport-climbing": 61805,
    "leisure-sport-cycling": 61806,
    "leisure-sport-diving": 61807,
    "leisure-sport-equestrian": 61808,
    "leisure-sport-free_flying": 61809,
    "leisure-sport-futsal": 61810,
    "leisure-sport-golf": 61811,
    "leisure-sport-gymnastics": 61812,
    "leisure-sport-handball": 61813,
    "leisure-sport-horse_racing": 61814,
    "leisure-sport-ice_hockey": 61815,
    "leisure-sport-karting": 61816,
    "leisure-sport-kitesurfing": 61817,
    "leisure-sport-motocross": 61818,
    "leisure-sport-motor": 61819,
    "leisure-sport-multi": 61820,
    "leisure-sport-orienteering": 61821,
    "leisure-sport-paddle_tennis": 61822,
    "leisure-sport-paintball": 61823,
    "leisure-sport-pelota": 61824,
    "leisure-sport-racquet": 61825,
    "leisure-sport-rowing": 61826,
    "leisure-sport-rugby_league": 61827,
    "leisure-sport-rugby_union": 61828,
    "leisure-sport-rugby": 61829,
    "leisure-sport-running": 61830,
    "leisure-sport-sailing": 61831,
    "leisure-sport-scuba_diving": 61832,
    "leisure-sport-shooting": 61833,
    "leisure-sport-skateboard": 61834,
    "leisure-sport-soccer": 61835,
    "leisure-sport-surfing": 61836,
    "leisure-sport-swimming": 61837,
    "leisure-sport-table_soccer": 61838,
    "leisure-sport-table_tennis": 61839,
    "leisure-sport-tennis": 61840,
    "leisure-sport-volleyball": 61841,
    "leisure-sport-water_ski": 61842,
    "leisure-sport-yoga": 61843,
    "leisure-sport": 61844,
    "leisure-sports_centre": 61845,
    "leisure-swimming_pool": 61846,
    "leisure-swimming": 61847,
    "leisure": 61848,
    "mobility-aeroway-aerodrome": 61849,
    "mobility-bicycle-bicycle_parking": 61850,
    "mobility-bicycle-bicycle_rental": 61851,
    "mobility-bicycle-bicycle": 61852,
    "mobility-bicycle-compressed_air": 61853,
    "mobility-bicycle-cycle_barrier": 61854,
    "mobility-bicycle-motorcycle_parking": 61855,
    "mobility-bicycle": 61856,
    "mobility-charging_station": 61857,
    "mobility-motorway-bus_station": 61858,
    "mobility-motorway-bus_stop": 61859,
    "mobility-motorway-car_pooling": 61860,
    "mobility-motorway-motorway_junction": 61861,
    "mobility-motorway-parking": 61862,
    "mobility-motorway-taxi": 61863,
    "mobility-motorway-toll_booth": 61864,
    "mobility-railway-halt": 61865,
    "mobility-railway-station": 61866,
    "mobility-railway-subway_entrance": 61867,
    "mobility-railway-tram_stop": 61868,
    "mobility-railway": 61869,
    "mobility-waterway-dock": 61870,
    "mobility-waterway-ferry_terminal": 61871,
    "mobility": 61872,
    "products-alcohol": 61873,
    "products-carpet": 61874,
    "products-chocolate": 61875,
    "products-craft-basket_maker": 61876,
    "products-craft-beekeeper": 61877,
    "products-craft-brewery": 61878,
    "products-craft-distillery": 61879,
    "products-craft-grinding_mill": 61880,
    "products-craft-handicraft": 61881,
    "products-craft-jeweller": 61882,
    "products-craft-leather": 61883,
    "products-craft-luthier": 61884,
    "products-craft-pottery": 61885,
    "products-craft-sculptor": 61886,
    "products-craft-winery": 61887,
    "products-craft": 61888,
    "products-deli": 61889,
    "products-farm": 61890,
    "products-oil_mill": 61891,
    "products-tailor": 61892,
    "products": 61893,
    "public_landmark-border_control": 61894,
    "public_landmark-brownfield": 61895,
    "public_landmark-cemetery": 61896,
    "public_landmark-college": 61897,
    "public_landmark-courthouse": 61898,
    "public_landmark-embassy": 61899,
    "public_landmark-grave_yard": 61900,
    "public_landmark-kindergarten": 61901,
    "public_landmark-library": 61902,
    "public_landmark-mall": 61903,
    "public_landmark-prison": 61904,
    "public_landmark-school": 61905,
    "public_landmark-university": 61906,
    "public_landmark-yes": 61907,
    "public_landmark": 61908,
    "remarkable-attraction_activity-aquarium": 61909,
    "remarkable-attraction_activity-attraction": 61910,
    "remarkable-attraction_activity-cave_entrance": 61911,
    "remarkable-attraction_activity-lighthouse": 61912,
    "remarkable-attraction_activity-spring": 61913,
    "remarkable-attraction_activity-theme_park": 61914,
    "remarkable-attraction_activity-viewpoint": 61915,
    "remarkable-attraction_activity-water_park": 61916,
    "remarkable-attraction_activity-waterfall": 61917,
    "remarkable-attraction_activity-zoo": 61918,
    "remarkable-natural_activity-beach_resort": 61919,
    "remarkable-natural_activity-beach": 61920,
    "remarkable-outdoor_activity-fishing": 61921,
    "remarkable-outdoor_activity-marina": 61922,
    "remarkable-outdoor_activity-stadium": 61923,
    "remarkable-outdoor_activity-swimming_area": 61924,
    "remarkable-outdoor_activity-winter_sports": 61925,
    "remarkable": 61926,
    "safety-care-centre": 61927,
    "safety-care-dentist": 61928,
    "safety-care-doctors": 61929,
    "safety-care-pharmacy": 61930,
    "safety-care-physiotherapist": 61931,
    "safety-care-veterinary": 61932,
    "safety-emergency-clinic": 61933,
    "safety-emergency-defibrillator": 61934,
    "safety-emergency-hospital": 61935,
    "safety-rescue-fire_station": 61936,
    "safety-rescue-life_ring": 61937,
    "safety-rescue-lifeguard_base": 61938,
    "safety-rescue-mountain_rescue": 61939,
    "safety-rescue-police": 61940,
    "safety-rescue-water_rescue_station": 61941,
    "safety": 61942,
    "services-atm": 61943,
    "services-bank": 61944,
    "services-car_parts": 61945,
    "services-car_repair": 61946,
    "services-copyshop": 61947,
    "services-dry_cleaning": 61948,
    "services-estate_agent": 61949,
    "services-fuel": 61950,
    "services-laundry": 61951,
    "services-massage": 61952,
    "services-office": 61953,
    "services-post_office": 61954,
    "services-ticket": 61955,
    "services-townhall": 61956,
    "services-travel_agency": 61957,
    "services": 61958,
    "shopping-animals-pet_grooming": 61959,
    "shopping-animals-pet": 61960,
    "shopping-culture-antiques": 61961,
    "shopping-culture-art": 61962,
    "shopping-culture-books": 61963,
    "shopping-culture-music": 61964,
    "shopping-fashion-accessories": 61965,
    "shopping-fashion-bag": 61966,
    "shopping-fashion-boutique": 61967,
    "shopping-fashion-clothes": 61968,
    "shopping-fashion-cosmetics": 61969,
    "shopping-fashion-fabric": 61970,
    "shopping-fashion-gift": 61971,
    "shopping-fashion-interior_decoration": 61972,
    "shopping-fashion-jewelry": 61973,
    "shopping-fashion-perfume": 61974,
    "shopping-fashion-perfumery": 61975,
    "shopping-fashion-second_hand": 61976,
    "shopping-fashion-shoes": 61977,
    "shopping-fashion-tattoo": 61978,
    "shopping-fashion-watches": 61979,
    "shopping-feed-beverages": 61980,
    "shopping-feed-coffee": 61981,
    "shopping-feed-confectionery": 61982,
    "shopping-feed-frozen_food": 61983,
    "shopping-feed-ice_cream": 61984,
    "shopping-sport_supply-bicycle": 61985,
    "shopping-sport_supply-outdoor": 61986,
    "shopping-supply-bed": 61987,
    "shopping-supply-camera": 61988,
    "shopping-supply-charity": 61989,
    "shopping-supply-computer": 61990,
    "shopping-supply-doityourself": 61991,
    "shopping-supply-electronics": 61992,
    "shopping-supply-erotic": 61993,
    "shopping-supply-furniture": 61994,
    "shopping-supply-general": 61995,
    "shopping-supply-hardware": 61996,
    "shopping-supply-hearing_aids": 61997,
    "shopping-supply-hifi": 61998,
    "shopping-supply-lamps": 61999,
    "shopping-supply-mobile_phone": 62000,
    "shopping-supply-motorcycle": 62001,
    "shopping-supply-musical_instrument": 62002,
    "shopping-supply-optician": 62003,
    "shopping-supply-stationery": 62004,
    "shopping-supply-toys": 62005,
    "shopping-supply-video_games": 62006,
    "shopping-supply-video": 62007,
    "shopping-supply-weapons": 62008,
    "shopping-supply-wholesale": 62009,
    "shopping": 62010
}